{"backend_name":"ibmq_london","backend_version":"1.1.0","qobj_id":"72ba2721-ef0b-4b37-94bd-1331f5d9755e","job_id":"5e866e92108dc200114329ff","success":true,"status":"Successful completion","time_taken":45.895347595214844,"results":[{"data":{"counts":{"0x0":1074,"0x1":599,"0x2":782,"0x3":973,"0x4":2508,"0x5":1018,"0x6":670,"0x7":568}},"header":{"clbit_labels":[["c2",0],["c2",1],["c2",2]],"creg_sizes":[["c2",3]],"memory_slots":3,"n_qubits":5,"name":"circuit1222","qreg_sizes":[["q",5]],"qubit_labels":[["q",0],["q",1],["q",2],["q",3],["q",4]]},"meas_level":2,"memory":false,"shots":8192,"success":true}],"date":"2020-04-02T23:07:38Z","execution_id":"a4c884a8-7536-11ea-a5f8-ac1f6b46a194","header":{"backend_name":"ibmq_london","backend_version":"1.1.0"}}